{"assets":[],"styles":[{"selectors":["#if8q"],"style":{"padding":"10px","float":"right","font-size":"20px"}},{"selectors":["#iifq"],"style":{"padding":"10px","float":"right","font-size":"20px"}},{"selectors":["#ii8v"],"style":{"padding":"10px","float":"right","font-size":"20px"}},{"selectors":["#i24g"],"style":{"min-height":"100px","background-color":"#00fff5"}},{"selectors":["#ikg4g"],"style":{"padding":"10px 10px 10px 10px","color":"#00ff26","text-align":"center","overflow":"auto auto","background-color":"rgba(0,112,4,0.73)"}},{"selectors":["#igd9j"],"style":{"font-size":"33px"}},{"selectors":["#ikg4g"],"style":{"top":"0px","left":"0px","visibility":"visible","display":"block","font-size":"33px"},"mediaText":"(max-width: 768px)","atRuleType":"media"}],"pages":[{"frames":[{"component":{"type":"wrapper","stylable":["background","background-color","background-image","background-repeat","background-attachment","background-position","background-size"],"attributes":{"id":"i8ay"},"components":[{"type":"text","attributes":{"id":"ikg4g"},"components":[{"tagName":"span","type":"text","attributes":{"id":"igd9j"},"components":[{"type":"textnode","content":"Espadon Du Travail"}]}]},{"type":"container","attributes":{"id":"i24g"},"components":[{"type":"text","attributes":{"id":"ii8v"},"components":[{"type":"textnode","content":"Contact"}]},{"type":"text","attributes":{"id":"iifq"},"components":[{"type":"textnode","content":"A propos de nous"}]},{"type":"text","attributes":{"id":"if8q"},"components":[{"type":"textnode","content":"Home"}]}]}]},"id":"IKFE89gn168fg0cf"}],"type":"main","id":"sPL8CWkwH30ktLu0"}],"settings":{"name":"Espadon Du Travail","lang":"fr,en,es","head":""},"name":"Espadon Du Travail","fonts":[],"symbols":[],"publication":{}}